jaco2.cp311-win_amd64.pyd
jaco2-4.5.data/data/dll_lib/CommandLayerEthernet.dll
jaco2-4.5.data/data/dll_lib/CommandLayerWindows.dll
jaco2-4.5.data/data/dll_lib/CommunicationLayerEthernet.dll
jaco2-4.5.data/data/dll_lib/CommunicationLayerWindows.dll
jaco2-4.5.dist-info/METADATA
jaco2-4.5.dist-info/WHEEL
jaco2-4.5.dist-info/top_level.txt
jaco2-4.5.dist-info/RECORD
