Metadata-Version: 2.1
Name: jaco2
Version: 4.5
Summary: A binding of simple jaco2 SDK commands for python
Author: Daniel Dharampal
